{
  "NM101": "Entity Identifier Code",
  "NM102": "Entity Type Qualifier",
  "NM103": "Name Last or Organization Name",
  "NM104": "Name First",
  "NM105": "Name Middle",
  "NM106": "Name Prefix",
  "NM107": "Name Suffix",
  "NM108": "Identification Code Qualifier",
  "NM109": "Identification Code",
  "CLM01": "Patient Control Number",
  "CLM02": "Total Claim Charge Amount",
  "CLM03": "Claim Filing Indicator Code",
  "CLM04": "Non-Institutional Claim Type Code",
  "CLM05": "Place of Service / Facility Code Qualifier / Claim Frequency",
  "CLM06": "Provider Signature on File",
  "CLM07": "Assignment or Plan Participation Code",
  "CLM08": "Benefits Assignment Certification Indicator",
  "CLM09": "Release of Information Code",
  "CLM10": "Patient Signature Source Code",
  "CLM11": "Related Causes Information",
  "DTP01": "Date/Time Qualifier",
  "DTP02": "Date Time Period Format Qualifier",
  "DTP03": "Date Value",
  "SV101": "Composite Medical Procedure Identifier",
  "SV102": "Line Item Charge Amount",
  "SV103": "Unit or Basis for Measurement Code",
  "SV104": "Service Unit Count",
  "SV105": "Place of Service Code",
  "SV106": "Service Type Code",
  "SV107": "Composite Diagnosis Code Pointer",
  "BHT01": "Hierarchical Structure Code",
  "BHT02": "Transaction Set Purpose Code",
  "BHT03": "Originator Application Transaction Identifier",
  "BHT04": "Transaction Set Creation Date",
  "BHT05": "Transaction Set Creation Time",
  "BHT06": "Transaction Type Code",
  "REF01": "Reference Identification Qualifier",
  "REF02": "Reference Identification",
  "PRV01": "Provider Code",
  "PRV02": "Reference Identification Qualifier",
  "PRV03": "Reference Identification",
  "N301": "Address Information",
  "N302": "Address Information 2",
  "N401": "City Name",
  "N402": "State or Province Code",
  "N403": "Postal Code",
  "N404": "Country Code",
  "INS01": "Member Indicator",
  "INS02": "Individual Relationship Code",
  "INS03": "Maintenance Type Code",
  "INS04": "Maintenance Reason Code",
  "CLP01": "Patient Control Number",
  "CLP02": "Claim Status Code",
  "CLP03": "Total Claim Charge Amount",
  "CLP04": "Claim Payment Amount",
  "CLP05": "Patient Responsibility Amount",
  "CLP06": "Claim Filing Indicator Code",
  "CLP07": "Payer Claim Control Number",
  "CLP08": "Facility Type Code",
  "CLP09": "Claim Frequency Type Code",
  "SVC01": "Composite Medical Procedure Identifier",
  "SVC02": "Line Item Charge Amount",
  "SVC03": "Line Item Provider Payment Amount",
  "SVC04": "Revenue Code",
  "SVC05": "Units of Service Paid Count",
  "SVC06": "Composite Diagnosis Code Pointer",
  "BPR01": "Transaction Handling Code",
  "BPR02": "Total Actual Provider Payment Amount",
  "BPR03": "Credit/Debit Flag Code",
  "BPR04": "Payment Method Code",
  "BPR05": "Payment Format Code",
  "BPR06": "DFI ID Number Qualifier",
  "BPR07": "DFI Identification Number",
  "BPR08": "Account Number Qualifier",
  "BPR09": "Account Number",
  "BPR10": "Originating Company Identifier",
  "BPR11": "Originating Company Supplemental Code",
  "BPR12": "DFI ID Number Qualifier (Receiver)",
  "BPR13": "DFI Identification Number (Receiver)",
  "BPR14": "Account Number Qualifier (Receiver)",
  "BPR15": "Account Number (Receiver)",
  "BPR16": "Check Issue or EFT Effective Date",
  "TRN01": "Trace Type Code",
  "TRN02": "Reference Identification",
  "TRN03": "Originating Company Identifier",
  "BGN01": "Transaction Set Purpose Code",
  "BGN02": "Reference Identification",
  "BGN03": "Transaction Set Creation Date",
  "BGN04": "Transaction Set Creation Time",
  "BGN05": "Time Code",
  "BGN06": "Reference Identifier",
  "BGN07": "Transaction Type Code",
  "BGN08": "Action Code"
}
